{
  "affected_bundles": [
    {
      "bundle": "kondratjev",
      "channel": "dev",
      "badge_type": "UPDATED",
      "apps": [
        {
          "app_name": "Lifesum",
          "package": "com.sillens.shapeupclub",
          "badge_type": "UPDATED APP"
        }
      ]
    },
    {
      "bundle": "kondratjev",
      "channel": "stable",
      "badge_type": "UPDATED",
      "apps": [
        {
          "app_name": "Lifesum",
          "package": "com.sillens.shapeupclub",
          "badge_type": "UPDATED APP"
        }
      ]
    },
    {
      "bundle": "hoo-dles",
      "channel": "dev",
      "badge_type": "UPDATED",
      "apps": [
        {
          "app_name": "Duolingo",
          "package": "com.duolingo",
          "badge_type": "UPDATED APP"
        },
        {
          "app_name": "Windy",
          "package": "com.windyty.android",
          "badge_type": "UPDATED APP"
        }
      ]
    }
  ]
}